thot/__about__.py
thot/__init__.py
thot/common.py
thot/database.py
thot/filter.py
thot/resources.py
thot/types.py
thot/bin/thot-local-database-aarch64-apple-darwin
thot/bin/thot-local-database-x86_64-apple-darwin
thot/bin/thot-local-database-x86_64-pc-windows-msvc.exe
thot/bin/thot-local-database-x86_64-unknown-linux-gnu
thot_data-0.10.0.post1.dist-info/METADATA
thot_data-0.10.0.post1.dist-info/WHEEL
thot_data-0.10.0.post1.dist-info/licenses/LICENSE-APACHE
thot_data-0.10.0.post1.dist-info/licenses/LICENSE-MIT
thot_data-0.10.0.post1.dist-info/RECORD
