Metadata-Version: 2.1
Name: thot-data
Version: 0.10.0.post1
Summary: Python library for Thot data analysis and management.
Project-URL: Issues, https://github.com/thot-data/thot-test/issues
Project-URL: Source, https://github.com/thot-data/thot
Project-URL: Homepage, https://thot.so
Author-email: Brian Carlsen <carlsen.bri@gmail.com>
License-Expression: MIT OR Apache-2.0
License-File: LICENSE-APACHE
License-File: LICENSE-MIT
Keywords: data analysis,data management
Classifier: License :: OSI Approved :: Apache Software License
Classifier: License :: OSI Approved :: MIT License
Classifier: Operating System :: OS Independent
Classifier: Programming Language :: Python :: 3
Requires-Python: >=3.7
Requires-Dist: pyzmq
